thingsboard_py/__init__.py
thingsboard_py/app.py
thingsboard_py-0.1.0.dist-info/LICENSE
thingsboard_py-0.1.0.dist-info/WHEEL
thingsboard_py-0.1.0.dist-info/METADATA
thingsboard_py-0.1.0.dist-info/RECORD
