Metadata-Version: 2.1
Name: thingsboard-py
Version: 0.1.0
Summary: Python client for ThingsBoard
Author: Parham Alvani
Author-email: parham.alvani@gmail.com
Requires-Python: >=3.10,<4.0
Classifier: Programming Language :: Python :: 3
Classifier: Programming Language :: Python :: 3.10
Requires-Dist: paho-mqtt (>=1.6.1,<2.0.0)
